cnspy_spatial_csv_formats/CSVSpatialFormat.py
cnspy_spatial_csv_formats/CSVSpatialFormatType.py
cnspy_spatial_csv_formats/ErrorRepresentationType.py
cnspy_spatial_csv_formats/EstimationErrorType.py
cnspy_spatial_csv_formats/PoseStructs.py
cnspy_spatial_csv_formats/__init__.py
test/__init__.py
test/test_CSVSpatialFormatType.py
test/test_EstimationErrorType.py
cnspy_spatial_csv_formats-0.2.2.dist-info/LICENCE
cnspy_spatial_csv_formats-0.2.2.dist-info/METADATA
cnspy_spatial_csv_formats-0.2.2.dist-info/WHEEL
cnspy_spatial_csv_formats-0.2.2.dist-info/top_level.txt
cnspy_spatial_csv_formats-0.2.2.dist-info/RECORD
