Metadata-Version: 2.1
Name: cnspy_spatial_csv_formats
Version: 0.2.2
Summary: Spatial formats for CSV files.
Home-page: https://github.com/aau-cns/cnspy_spatial_csv_formats/
Author: Roland Jung
Author-email: roland.jung@aau.at
Project-URL: Bug Tracker, https://github.com/aau-cns/cnspy_spatial_csv_formats/issues
Classifier: Development Status :: 4 - Beta
Classifier: Intended Audience :: Developers
Classifier: Programming Language :: Python :: 3
Classifier: License :: OSI Approved :: GNU General Public License v3 (GPLv3)
Classifier: Operating System :: OS Independent
Requires-Python: >=3.6
License-File: LICENCE
Requires-Dist: numpy
